lianpwn/__init__.py
lianpwn/cli.py
lianpwn/nocli.py
lianpwn/template_gen.py
lianpwn-1.0.4.dist-info/LICENSE
lianpwn-1.0.4.dist-info/METADATA
lianpwn-1.0.4.dist-info/WHEEL
lianpwn-1.0.4.dist-info/entry_points.txt
lianpwn-1.0.4.dist-info/top_level.txt
lianpwn-1.0.4.dist-info/RECORD
