Metadata-Version: 2.1
Name: lianpwn
Version: 1.0.4
Summary: lianpwn based on pwncli
Home-page: https://eastxuelian.nebuu.la/
Author: eastXueLian
Author-email: eastxuelian@gmail.com
Classifier: Programming Language :: Python :: 3
Classifier: License :: OSI Approved :: MIT License
Classifier: Operating System :: OS Independent
License-File: LICENSE
Requires-Dist: click
Requires-Dist: pwntools
Requires-Dist: pwncli
